canfix/__init__.py
canfix/canfix.json
canfix/canfix.xml
canfix/globals.py
canfix/protocol.py
canfix/utils.py
canfix/messages/__init__.py
canfix/messages/bitrateset.py
canfix/messages/edparameter.py
canfix/messages/nodealarm.py
canfix/messages/nodeconfiguration.py
canfix/messages/nodedescription.py
canfix/messages/nodeidentification.py
canfix/messages/nodeidset.py
canfix/messages/nodereport.py
canfix/messages/nodespecific.py
canfix/messages/nodestatus.py
canfix/messages/parameter.py
canfix/messages/parameterset.py
canfix/messages/twoway.py
canfix/messages/twowayconnection.py
canfix/messages/updatefirmware.py
tests/__init__.py
tests/dataconversion.py
tests/msgtypes.py
tests/node_alarm.py
tests/node_specific.py
tests/parameter.py
tests/two_way_msg.py
tests/utils.py
python_canfix-0.3.0.dist-info/LICENSE
python_canfix-0.3.0.dist-info/METADATA
python_canfix-0.3.0.dist-info/WHEEL
python_canfix-0.3.0.dist-info/top_level.txt
python_canfix-0.3.0.dist-info/RECORD
