Metadata-Version: 2.1
Name: python-canfix
Version: 0.3.0
Summary: Python CAN-FIX Library
Home-page: https://github.com/birkelbach/python-canfix
Author: Phil Birkelbach
Author-email: phil@petrasoft.net
License: GNU General Public License Version 2
Platform: UNKNOWN
License-File: LICENSE
Requires-Dist: python-can
